simplefin4py/__init__.py
simplefin4py/const.py
simplefin4py/exceptions.py
simplefin4py/model.py
simplefin4py/simplefin.py
simplefin4py-0.0.17.dist-info/LICENSE
simplefin4py-0.0.17.dist-info/METADATA
simplefin4py-0.0.17.dist-info/WHEEL
simplefin4py-0.0.17.dist-info/RECORD
