Metadata-Version: 2.1
Name: simplefin4py
Version: 0.0.17
Summary: 
License: MIT
Author: Jeef
Author-email: jeeftor@users.noreply.github.com
Requires-Python: >=3.11,<4.0
Classifier: License :: OSI Approved :: MIT License
Classifier: Programming Language :: Python :: 3
Classifier: Programming Language :: Python :: 3.11
Classifier: Programming Language :: Python :: 3.12
Requires-Dist: aiohttp (>=3.9.1)
Requires-Dist: dataclasses-json (>=0.6.3,<0.7.0)
